stackoverflow_mcp/__init__.py
stackoverflow_mcp/__main__.py
stackoverflow_mcp/api.py
stackoverflow_mcp/env.py
stackoverflow_mcp/formatter.py
stackoverflow_mcp/server.py
stackoverflow_mcp/types.py
stackoverflow_mcp-0.1.3.dist-info/METADATA
stackoverflow_mcp-0.1.3.dist-info/WHEEL
stackoverflow_mcp-0.1.3.dist-info/entry_points.txt
stackoverflow_mcp-0.1.3.dist-info/licenses/LICENSE
stackoverflow_mcp-0.1.3.dist-info/RECORD
