Metadata-Version: 2.4
Name: stackoverflow-mcp
Version: 0.1.3
Summary: Stack Overflow MCP server for LLM applications
Project-URL: Homepage, https://github.com/CodexVeritax/stackoverflow-mcp-server
Project-URL: Issues, https://github.com/CodexVeritax/stackoverflow-mcp-server/issues
Author-email: Mark Nawar <markadelnawar@gmail.com>
License-Expression: MIT
License-File: LICENSE
Classifier: License :: OSI Approved :: MIT License
Classifier: Operating System :: OS Independent
Classifier: Programming Language :: Python :: 3.10
Classifier: Programming Language :: Python :: 3.11
Classifier: Programming Language :: Python :: 3.12
Requires-Python: >=3.10
Requires-Dist: httpx>=0.24.0
Requires-Dist: mcp>=0.7.0
Requires-Dist: python-dotenv>=1.0.0
Provides-Extra: dev
Requires-Dist: pytest-asyncio>=0.21.0; extra == 'dev'
Requires-Dist: pytest-cov>=4.0.0; extra == 'dev'
Requires-Dist: pytest>=7.0.0; extra == 'dev'
